Workbook

Sheet README
A1: ITW Polymers & Fluids — Rain-X Wiper & Glass Care Division · Q3 FY26 Leadership Data Pack
A2: TRAINING SAMPLE. Every company, plant, customer, person and number in this workbook is fictional and was created for the Microsoft 365 Copilot leadership enablement session. It is not ITW data and must not be used for any business decision.
A4: Purpose: this workbook is the data spine for the session. Leaders point Copilot, Analyst and the P&F Leadership Briefing agent at these sheets and practise turning raw divisional data into a decision, a briefing and a follow-up.
A6: Sheet | B6: What it holds | C6: Used in which part of the session
A7: P&L Summary | B7: Q3 revenue and gross margin by product line, actual vs plan vs prior year | C7: Module 1 briefing prep and Module 3 Excel / Analyst demo
A8: Price Volume Mix | B8: Revenue bridge decomposing the year-on-year change into price, volume, mix and FX | C8: Module 3 trend analysis and Module 5 pricing decision scenario
A9: Plant Operations | B9: OEE, scrap, on-time delivery, safety TRIR and output vs plan for six plants | C9: Module 5 operations scenario and the agent knowledge source
A10: Customer Margin | B10: Top 12 customers with revenue, gross margin, renewal date and price action status | C10: Module 1 briefing prep and Module 5 commercial scenario
A11: Orders & Backlog | B11: Rolling 12 months of orders, shipments, ending backlog and book-to-bill | C11: Module 3 trend analysis with the Analyst agent
A12: Talent & Headcount | B12: Headcount, open requisitions, attrition, tenure, engagement and Copilot licence coverage by function | C12: Module 5 talent scenario and Module 6 ROI baseline
A13: Copilot ROI Model | B13: Value model and leader adoption scorecard with baseline, 30-day and 90-day targets | C13: Module 6 measuring ROI and productivity gains
A15: Colour legend
A16: Blue text | B16: A hardcoded input you can change to run a scenario
A17: Black text | B17: A live formula — it recalculates when you change an input
A18: Green text | B18: A link pulling a value from another sheet in this workbook
A19: Red fill | B19: A conditional-format flag: below OEE, delivery, margin or book-to-bill threshold, or above the scrap and attrition threshold
A20: Teal fill | B20: A total, average or headline outcome row
A22: Key assumptions you should replace before using any of this with a real audience
A23: Hours saved per leader per week, hours saved per other licensed user per week, both fully loaded cost rates and the monthly licence cost on the Copilot ROI Model sheet are PLACEHOLDERS. Substitute ITW finance rates and your own measured survey results before quoting any value figure.
A24: The adoption realization factor of 65% is a deliberately conservative planning assumption, not an observed result.
A25: The adoption scorecard baselines are illustrative starting points. Pull your real baselines from the Microsoft 365 admin centre Copilot usage reporting before the session.

Sheet P&L Summary
A1: ITW Polymers & Fluids — Rain-X Wiper & Glass Care Division · Q3 FY26 P&L Summary (illustrative sample data)
A2: Product Line | B2: Q3 Revenue Actual ($K) | C2: Q3 Revenue Plan ($K) | D2: PY Q3 Revenue ($K) | E2: Q3 Gross Margin $ Actual ($K) | F2: Q3 Gross Margin $ Plan ($K) | G2: Revenue vs Plan ($K) | H2: Revenue vs Plan % | I2: YoY Revenue % | J2: Gross Margin % Actual | K2: Gross Margin % Plan | L2: Gross Margin Variance (pts)
A3: Wiper Blades - Premium | B3: 24850 | C3: 26200 | D3: 23900 | E3: 9190 | F3: 10218 | G3: =B3-C3 | H3: =B3/C3-1 | I3: =B3/D3-1 | J3: =E3/B3 | K3: =F3/C3 | L3: =J3-K3
A4: Wiper Blades - Conventional | B4: 18420 | C4: 17900 | D4: 16850 | E4: 7000 | F4: 6802 | G4: =B4-C4 | H4: =B4/C4-1 | I4: =B4/D4-1 | J4: =E4/B4 | K4: =F4/C4 | L4: =J4-K4
A5: Washer Fluids | B5: 15260 | C5: 16800 | D5: 16100 | E5: 4730 | F5: 5712 | G5: =B5-C5 | H5: =B5/C5-1 | I5: =B5/D5-1 | J5: =E5/B5 | K5: =F5/C5 | L5: =J5-K5
A6: Glass Treatments | B6: 12940 | C6: 12100 | D6: 11400 | E6: 5050 | F6: 4598 | G6: =B6-C6 | H6: =B6/C6-1 | I6: =B6/D6-1 | J6: =E6/B6 | K6: =F6/C6 | L6: =J6-K6
A7: Winter & De-Icer Fluids | B7: 9780 | C7: 10400 | D7: 10050 | E7: 3130 | F7: 3536 | G7: =B7-C7 | H7: =B7/C7-1 | I7: =B7/D7-1 | J7: =E7/B7 | K7: =F7/C7 | L7: =J7-K7
A8: Wiper Refills & Accessories | B8: 7310 | C8: 6500 | D8: 5980 | E8: 3290 | F8: 2860 | G8: =B8-C8 | H8: =B8/C8-1 | I8: =B8/D8-1 | J8: =E8/B8 | K8: =F8/C8 | L8: =J8-K8
A9: Division Total | B9: =SUM(B3:B8) | C9: =SUM(C3:C8) | D9: =SUM(D3:D8) | E9: =SUM(E3:E8) | F9: =SUM(F3:F8) | G9: =B9-C9 | H9: =B9/C9-1 | I9: =B9/D9-1 | J9: =E9/B9 | K9: =F9/C9 | L9: =J9-K9

Sheet Price Volume Mix
A1: Q3 FY26 Revenue Bridge — Price / Volume / Mix / FX vs Prior Year (illustrative sample data)
A2: Product Line | B2: PY Q3 Revenue ($K) | C2: Price Impact ($K) | D2: Volume Impact ($K) | E2: Mix Impact ($K) | F2: FX Impact ($K) | G2: Q3 FY26 Revenue ($K) | H2: Total Change ($K) | I2: Total Change %
A3: Wiper Blades - Premium | B3: 23900 | C3: 1780 | D3: -1090 | E3: 190 | F3: 70 | G3: =SUM(B3:F3) | H3: =G3-B3 | I3: =H3/B3
A4: Wiper Blades - Conventional | B4: 16850 | C4: 940 | D4: 520 | E4: 65 | F4: 45 | G4: =SUM(B4:F4) | H4: =G4-B4 | I4: =H4/B4
A5: Washer Fluids | B5: 16100 | C5: 410 | D5: -1320 | E5: 40 | F5: 30 | G5: =SUM(B5:F5) | H5: =G5-B5 | I5: =H5/B5
A6: Glass Treatments | B6: 11400 | C6: 720 | D6: 690 | E6: 105 | F6: 25 | G6: =SUM(B6:F6) | H6: =G6-B6 | I6: =H6/B6
A7: Winter & De-Icer Fluids | B7: 10050 | C7: 260 | D7: -620 | E7: 75 | F7: 15 | G7: =SUM(B7:F7) | H7: =G7-B7 | I7: =H7/B7
A8: Wiper Refills & Accessories | B8: 5980 | C8: 380 | D8: 860 | E8: 80 | F8: 10 | G8: =SUM(B8:F8) | H8: =G8-B8 | I8: =H8/B8
A9: Division Total | B9: =SUM(B3:B8) | C9: =SUM(C3:C8) | D9: =SUM(D3:D8) | E9: =SUM(E3:E8) | F9: =SUM(F3:F8) | G9: =SUM(G3:G8) | H9: =G9-B9 | I9: =H9/B9
A11: Check: bridge total less P&L Summary division revenue (should be 0) | G11: =G9-'P&L Summary'!B9

Sheet Plant Operations
A1: Q3 FY26 Plant Operations Scorecard — Rain-X Wiper & Glass Care Division (illustrative sample data)
A2: Plant | B2: Location | C2: OEE | D2: Scrap Rate | E2: On-Time Delivery | F2: Safety TRIR | G2: Q3 Output (K units) | H2: Q3 Plan Output (K units) | I2: Output vs Plan %
A3: Elgin Blade Works | B3: Elgin, IL | C3: 0.782 | D3: 0.041 | E3: 0.943 | F3: 0.82 | G3: 1240 | H3: 1300 | I3: =G3/H3-1
A4: Rockford Fluids | B4: Rockford, IL | C4: 0.714 | D4: 0.062 | E4: 0.887 | F4: 1.45 | G4: 980 | H4: 1120 | I4: =G4/H4-1
A5: Greenville Glass Care | B5: Greenville, SC | C5: 0.836 | D5: 0.028 | E5: 0.968 | F5: 0.41 | G5: 1510 | H5: 1470 | I5: =G5/H5-1
A6: Monterrey Blade Assembly | B6: Monterrey, MX | C6: 0.759 | D6: 0.049 | E6: 0.912 | F6: 1.1 | G6: 1180 | H6: 1250 | I6: =G6/H6-1
A7: Gdansk Blade Works | B7: Gdansk, PL | C7: 0.801 | D7: 0.035 | E7: 0.951 | F7: 0.66 | G7: 860 | H7: 840 | I7: =G7/H7-1
A8: Suzhou Wiper Components | B8: Suzhou, CN | C8: 0.723 | D8: 0.058 | E8: 0.894 | F8: 0.95 | G8: 1020 | H8: 1150 | I8: =G8/H8-1
A9: Division (avg / total) | C9: =AVERAGE(C3:C8) | D9: =AVERAGE(D3:D8) | E9: =AVERAGE(E3:E8) | F9: =AVERAGE(F3:F8) | G9: =SUM(G3:G8) | H9: =SUM(H3:H8) | I9: =G9/H9-1

Sheet Customer Margin
A1: Q3 FY26 Top-12 Customer Revenue & Margin — Rain-X Wiper & Glass Care Division (illustrative sample data)
A2: Customer | B2: Segment Served | C2: Q3 Revenue ($K) | D2: Gross Margin % | E2: Contract Renewal (YYYY-MM-DD) | F2: Price Action Status | G2: Gross Margin $ ($K) | H2: % of Division Revenue
A3: Northwind Auto Parts | B3: National Retail | C3: 9420 | D3: 0.286 | E3: 46477 | F3: Increase proposed - pending | G3: =C3*D3 | H3: =C3/'P&L Summary'!$B$9
A4: Cascade Service Group | B4: Installer Network | C4: 6180 | D4: 0.441 | E4: 46934 | F4: No action needed | G4: =C4*D4 | H4: =C4/'P&L Summary'!$B$9
A5: Meridian Mass Retail | B5: Mass Retail | C5: 5940 | D5: 0.318 | E5: 46387 | F5: Increase accepted | G5: =C5*D5 | H5: =C5/'P&L Summary'!$B$9
A6: Halverson Fleet Services | B6: Fleet | C6: 4310 | D6: 0.372 | E6: 46660 | F6: No action needed | G6: =C6*D6 | H6: =C6/'P&L Summary'!$B$9
A7: Tri-State Distribution | B7: Wholesale Distribution | C7: 3880 | D7: 0.244 | E7: 46356 | F7: Increase proposed - resisted | G7: =C7*D7 | H7: =C7/'P&L Summary'!$B$9
A8: Bluegrass Farm & Auto | B8: Rural Retail | C8: 3620 | D8: 0.351 | E8: 46538 | F8: Increase accepted | G8: =C8*D8 | H8: =C8/'P&L Summary'!$B$9
A9: Vantage Glass OEM | B9: Glass OEM | C9: 3150 | D9: 0.478 | E9: 47149 | F9: No action needed | G9: =C9*D9 | H9: =C9/'P&L Summary'!$B$9
A10: Keystone Travel Centers | B10: Travel Retail | C10: 2970 | D10: 0.297 | E10: 46326 | F10: Increase proposed - pending | G10: =C10*D10 | H10: =C10/'P&L Summary'!$B$9
A11: Lakeshore Car Care | B11: Quick Lube | C11: 2540 | D11: 0.331 | E11: 46599 | F11: No action needed | G11: =C11*D11 | H11: =C11/'P&L Summary'!$B$9
A12: Orion Online | B12: E-commerce | C12: 2310 | D12: 0.412 | E12: 46811 | F12: Increase accepted | G12: =C12*D12 | H12: =C12/'P&L Summary'!$B$9
A13: Redcliff Fleet Supply | B13: Fleet Supply | C13: 1980 | D13: 0.226 | E13: 46387 | F13: Under margin review | G13: =C13*D13 | H13: =C13/'P&L Summary'!$B$9
A14: Summit Collision Centers | B14: Collision Repair | C14: 1760 | D14: 0.389 | E14: 46507 | F14: No action needed | G14: =C14*D14 | H14: =C14/'P&L Summary'!$B$9
A15: Top 12 Total | C15: =SUM(C3:C14) | D15: =G15/C15 | G15: =SUM(G3:G14) | H15: =SUM(H3:H14)

Sheet Orders & Backlog
A1: Rolling 12-Month Orders, Shipments and Backlog — Rain-X Wiper & Glass Care Division (illustrative sample data)
A2: Month | B2: Orders ($K) | C2: Shipments ($K) | D2: Ending Backlog ($K) | E2: Book-to-Bill
A3: 45931 | B3: 29100 | C3: 28400 | D3: =$B$17+B3-C3 | E3: =B3/C3
A4: 45962 | B4: 27800 | C4: 28900 | D4: =D3+B4-C4 | E4: =B4/C4
A5: 45992 | B5: 31600 | C5: 30200 | D5: =D4+B5-C5 | E5: =B5/C5
A6: 46023 | B6: 26900 | C6: 27800 | D6: =D5+B6-C6 | E6: =B6/C6
A7: 46054 | B7: 28400 | C7: 27600 | D7: =D6+B7-C7 | E7: =B7/C7
A8: 46082 | B8: 32100 | C8: 30900 | D8: =D7+B8-C8 | E8: =B8/C8
A9: 46113 | B9: 30200 | C9: 29400 | D9: =D8+B9-C9 | E9: =B9/C9
A10: 46143 | B10: 29800 | C10: 30600 | D10: =D9+B10-C10 | E10: =B10/C10
A11: 46174 | B11: 33400 | C11: 31100 | D11: =D10+B11-C11 | E11: =B11/C11
A12: 46204 | B12: 28600 | C12: 29900 | D12: =D11+B12-C12 | E12: =B12/C12
A13: 46235 | B13: 30900 | C13: 29200 | D13: =D12+B13-C13 | E13: =B13/C13
A14: 46266 | B14: 27400 | C14: 29400 | D14: =D13+B14-C14 | E14: =B14/C14
A15: 12-Month Total / Ending | B15: =SUM(B3:B14) | C15: =SUM(C3:C14) | D15: =D14 | E15: =B15/C15
A17: Opening backlog at Sep-25 ($K) | B17: 31200
A18: Check: opening + orders - shipments - ending backlog (should be 0) | D18: =B17+B15-C15-D15

Sheet Talent & Headcount
A1: Q3 FY26 Talent, Attrition and Copilot Licensing by Function (illustrative sample data)
A2: Function | B2: Headcount | C2: Open Requisitions | D2: Voluntary Attrition | E2: Average Tenure (yrs) | F2: Engagement Score | G2: Copilot Licensed Users | H2: Copilot Coverage %
A3: Operations | B3: 1240 | C3: 62 | D3: 0.142 | E3: 6.8 | F3: 71 | G3: 180 | H3: =G3/B3
A4: Commercial & Sales | B4: 186 | C4: 14 | D4: 0.098 | E4: 5.2 | F4: 78 | G4: 186 | H4: =G4/B4
A5: Engineering | B5: 148 | C5: 19 | D5: 0.071 | E5: 8.4 | F5: 82 | G5: 148 | H5: =G5/B5
A6: Quality | B6: 96 | C6: 7 | D6: 0.083 | E6: 7.1 | F6: 76 | G6: 96 | H6: =G6/B6
A7: Supply Chain | B7: 112 | C7: 9 | D7: 0.115 | E7: 4.9 | F7: 69 | G7: 112 | H7: =G7/B7
A8: Finance | B8: 54 | C8: 3 | D8: 0.056 | E8: 9.3 | F8: 84 | G8: 54 | H8: =G8/B8
A9: Human Resources | B9: 28 | C9: 2 | D9: 0.061 | E9: 6.2 | F9: 80 | G9: 28 | H9: =G9/B9
A10: Information Technology | B10: 42 | C10: 5 | D10: 0.074 | E10: 5.6 | F10: 79 | G10: 42 | H10: =G10/B10
A11: Division Total / Weighted Avg | B11: =SUM(B3:B10) | C11: =SUM(C3:C10) | D11: =SUMPRODUCT(D3:D10,B3:B10)/B11 | E11: =SUMPRODUCT(E3:E10,B3:B10)/B11 | F11: =SUMPRODUCT(F3:F10,B3:B10)/B11 | G11: =SUM(G3:G10) | H11: =G11/B11

Sheet Copilot ROI Model
A1: Copilot Value & Adoption Model — Rain-X Wiper & Glass Care Division Leadership (illustrative assumptions)
A3: Input assumption | B3: Value | C3: Unit and source
A4: Leaders in scope | B4: 100 | C4: People · session audience size supplied by ITW
A5: Total Copilot-licensed users in division | B5: ='Talent & Headcount'!G11 | C5: People · linked from the Talent & Headcount sheet
A6: Hours saved per leader per week | B6: 3.5 | C6: Hours · PLACEHOLDER — replace with your own measured pulse-survey result
A7: Hours saved per other licensed user per week | B7: 1.8 | C7: Hours · PLACEHOLDER — replace with your own measured pulse-survey result
A8: Leader fully loaded cost rate | B8: 145 | C8: $ per hour · PLACEHOLDER — replace with ITW finance rate
A9: Other employee fully loaded cost rate | B9: 78 | C9: $ per hour · PLACEHOLDER — replace with ITW finance rate
A10: Productive working weeks per year | B10: 46 | C10: Weeks · 52 weeks less holiday and PTO
A11: Adoption realization factor | B11: 0.65 | C11: % of theoretical saving actually realized · conservative planning assumption
A12: License cost per user per month | B12: 30 | C12: $ per user per month · PLACEHOLDER — confirm ITW contracted rate
A14: Calculated outcome | B14: Value | C14: How it is derived
A15: Leader hours released per year | B15: =B4*B6*B10*B11 | C15: Leaders x hours per week x working weeks x realization factor
A16: Other employee hours released per year | B16: =(B5-B4)*B7*B10*B11 | C16: (Licensed users less leaders) x hours per week x working weeks x realization factor
A17: Total hours released per year | B17: =B15+B16 | C17: Leader hours plus other employee hours
A18: Value of leader time released | B18: =B15*B8 | C18: Leader hours x leader loaded rate
A19: Value of other employee time released | B19: =B16*B9 | C19: Employee hours x employee loaded rate
A20: Gross annual value | B20: =B18+B19 | C20: Leader value plus employee value
A21: Annual license cost | B21: =B5*B12*12 | C21: Licensed users x monthly cost x 12
A22: Net annual value | B22: =B20-B21 | C22: Gross annual value less annual license cost
A23: Return multiple on license spend | B23: =B20/B21 | C23: Gross annual value divided by annual license cost
A24: Payback period | B24: =B21/(B20/12) | C24: Annual license cost divided by average monthly gross value
A25: Value released per leader per year | B25: =B18/B4 | C25: Value of leader time divided by leaders in scope
A27: Leader adoption scorecard | B27: Baseline (Q3) | C27: 30-day target | D27: 90-day target | E27: Where the number comes from
A28: Leaders using Copilot at least weekly | B28: 0.41 | C28: 0.75 | D28: 0.95 | E28: Microsoft 365 admin centre Copilot usage report
A29: Leaders using an agent at least weekly | B29: 0.08 | C29: 0.35 | D29: 0.7 | E29: Agent usage reporting
A30: Leadership meetings with a Copilot recap applied | B30: 0.22 | C30: 0.5 | D30: 0.8 | E30: Teams meeting reporting
A31: Decision memos drafted with Copilot | B31: 0.05 | C31: 0.3 | D31: 0.6 | E31: Divisional decision log review
A32: Leaders reporting more than 2 hours saved per week | B32: 0.18 | C32: 0.45 | D32: 0.75 | E32: Quarterly leadership pulse survey
A33: Leaders who published a Copilot Page or Notebook | B33: 0.03 | C33: 0.25 | D33: 0.55 | E33: Copilot Pages usage reporting
